_gaussianfft.so
gaussianfft/__init__.py
gaussianfft/__init__.pyi
gaussianfft/_version.py
gaussianfft/advanced/__init__.py
gaussianfft/advanced/__init__.pyi
gaussianfft/util/__init__.py
gaussianfft/util/empirical_variogram.py
gaussianfft/util/empirical_variogram2.py
gaussianfft/util/padding_analyzer.py
gaussianfft/util/resource_extrapolator.py
gaussianfft-1.1.2.dist-info/METADATA
gaussianfft-1.1.2.dist-info/WHEEL
gaussianfft-1.1.2.dist-info/entry_points.txt
gaussianfft-1.1.2.dist-info/licenses/LICENSE.txt
gaussianfft-1.1.2.dist-info/RECORD
