Metadata-Version: 2.1
Name: gaussianfft
Version: 1.1.2
Summary: A fast library for simulating Gaussian Random Fields, using the fast Fourier transform
Keywords: Stochastic simulation Gaussian random field FFT
Author: Norwegian Computing Center
Author-Email: Sindre Nistad <snis@equinor.com>
License: BSD 2-Clause License
Classifier: Development Status :: 5 - Production/Stable
Classifier: License :: OSI Approved :: BSD License
Classifier: Operating System :: MacOS :: MacOS X
Classifier: Operating System :: POSIX :: Linux
Classifier: Programming Language :: C++
Classifier: Programming Language :: Python :: 3
Classifier: Programming Language :: Python :: 3.7
Classifier: Programming Language :: Python :: 3.8
Classifier: Programming Language :: Python :: 3.9
Classifier: Programming Language :: Python :: 3.10
Classifier: Programming Language :: Python :: 3.11
Classifier: Programming Language :: Python :: 3.12
Classifier: Programming Language :: Python :: Implementation :: CPython
Classifier: Topic :: Scientific/Engineering
Classifier: Topic :: Scientific/Engineering :: Mathematics
Classifier: Topic :: Software Development :: Libraries :: Python Modules
Project-URL: Homepage, https://equinor.com
Project-URL: Repository, https://github.com/equinor/gaussianfft
Project-URL: Issues, https://github.com/equinor/gaussianfft/issues
Requires-Python: >=3.6
Requires-Dist: numpy
Requires-Dist: scipy; extra == "util"
Provides-Extra: util
